{
  "repository": {
    "name": "modelsAPI",
    "path": "/home/bighub/ComplexSpace/modelsAPI"
  },
  "commits": [
    {
      "hash": "64a3fefbba8b34c1b09ba11ed98eda9a62d96f64",
      "author": "Ethan",
      "author_email": "ems910@outlook.com",
      "author_date": "2024-11-30T11:29:48",
      "commit_date": "2024-11-30T11:29:48",
      "message": "hope this works"
    },
    {
      "hash": "13587bf323be0f6b4755ad3b6634b23030e7c3c7",
      "author": "Ethan",
      "author_email": "ems910@outlook.com",
      "author_date": "2024-11-28T14:14:02",
      "commit_date": "2024-11-28T14:14:02",
      "message": "new funtion"
    },
    {
      "hash": "943b5a04c3c1e9a9c923f19f71f3bc32b02a1042",
      "author": "Ethan",
      "author_email": "ems910@outlook.com",
      "author_date": "2024-11-28T13:50:54",
      "commit_date": "2024-11-28T13:50:54",
      "message": "fixed ddids"
    },
    {
      "hash": "b7fdc303ca7d6abeaba6125d75d90734eab5de6a",
      "author": "Ethan",
      "author_email": "ems910@outlook.com",
      "author_date": "2024-11-27T15:03:16",
      "commit_date": "2024-11-27T15:03:16",
      "message": "i can't belive its running again so fast"
    },
    {
      "hash": "46c9cc9832cbabf0a168266f991e117100ac531e",
      "author": "Ethan",
      "author_email": "ems910@outlook.com",
      "author_date": "2024-11-27T14:15:50",
      "commit_date": "2024-11-27T14:15:50",
      "message": "before i break it"
    },
    {
      "hash": "c988665f7e63830f2176091887231d4432f4d55d",
      "author": "Ethan",
      "author_email": "ems910@outlook.com",
      "author_date": "2024-11-27T13:31:26",
      "commit_date": "2024-11-27T13:31:26",
      "message": "finally a modular core tool"
    },
    {
      "hash": "3f63c9b91aaf4b42530b60fdf621a63f4f61aa95",
      "author": "Ethan",
      "author_email": "ems910@outlook.com",
      "author_date": "2024-11-27T12:53:39",
      "commit_date": "2024-11-27T12:53:39",
      "message": "starter"
    },
    {
      "hash": "a60583cf64d2fdce7ef53bb8feb36d1024dd7fe3",
      "author": "Ethan",
      "author_email": "ems910@outlook.com",
      "author_date": "2024-11-27T12:53:23",
      "commit_date": "2024-11-27T12:53:23",
      "message": "i m"
    }
  ],
  "branches": [
    {
      "name": "master",
      "is_current": true
    }
  ],
  "code_stats": {
    "total_lines": 8575,
    "file_count": 22664,
    "file_extensions": {
      ".txt": 190,
      ".py": 12889,
      ".db": 1,
      ".cfg": 6,
      ".pyc": 12882,
      ".json": 15,
      ".pth": 1,
      ".typed": 52,
      ".md": 12,
      ".pyx": 95,
      ".build": 26,
      ".so": 338,
      ".pxd": 85,
      ".pxi": 19,
      ".h": 9626,
      ".cpp": 64,
      ".c": 14,
      ".tp": 24,
      ".rst": 16,
      ".jpg": 2,
      ".gz": 104,
      ".csv": 37,
      ".css": 6,
      ".tab": 8,
      ".zi": 2,
      ".12": 11,
      ".10": 1,
      ".2": 2,
      ".11": 4,
      ".9": 9,
      ".4": 2,
      ".1": 8,
      ".hpp": 96,
      ".zip": 1,
      ".egg": 1,
      ".toml": 2,
      ".pyi": 396,
      ".tpl": 7,
      ".PSF": 1,
      ".0": 17,
      ".j2": 2,
      ".js": 71,
      ".map": 5,
      ".gzip": 5,
      ".pkl": 11,
      ".bz2": 10,
      ".npy": 31,
      ".z": 3,
      ".xz": 5,
      ".lzma": 5,
      ".yaml": 6,
      ".cu": 9,
      ".ini": 4,
      ".bzl": 1,
      ".bazel": 1,
      ".in": 1,
      ".pem": 2,
      ".crt": 1,
      ".key": 1,
      ".mo": 1,
      ".po": 1,
      ".xml": 2,
      ".html": 6,
      ".png": 10,
      ".g4": 2,
      ".al": 16,
      ".lark": 2,
      ".xsl": 3,
      ".template": 1,
      ".f90": 55,
      ".f": 21,
      ".pyf": 5,
      ".inc": 1,
      ".f95": 1,
      ".a": 2,
      ".pc": 1,
      ".fits": 1,
      ".npz": 22,
      ".woff": 20,
      ".woff2": 39,
      ".ttf": 20,
      ".svg": 6,
      ".gif": 1,
      ".BSD": 2,
      ".APACHE": 2,
      ".cuh": 58,
      ".1801": 6,
      ".cc": 24,
      ".feather": 1,
      ".parquet": 4,
      ".orc": 4,
      ".APACHE2": 1,
      ".MIT": 1,
      ".mjs": 2,
      ".cmake": 31,
      ".sh": 1,
      ".3": 1,
      ".16": 1,
      ".15": 1,
      ".markdown-it": 1,
      ".A99": 2,
      ".B99": 2,
      ".asm": 2,
      ".obj": 2,
      ".cmd": 2,
      ".bc": 3,
      ".arff": 16,
      ".sav": 47,
      ".dat": 29,
      ".nc": 3,
      ".wav": 22,
      ".ani": 1,
      ".mat": 109,
      ".exe": 8,
      ".tmpl": 2,
      ".h5": 3,
      ".ps1": 1,
      ".fish": 1,
      ".csh": 1
    }
  },
  "summary": {
    "name": "modelsAPI",
    "num_commits": 8,
    "num_branches": 1,
    "total_lines": 8575,
    "file_count": 22664,
    "file_extensions": {
      ".txt": 190,
      ".py": 12889,
      ".db": 1,
      ".cfg": 6,
      ".pyc": 12882,
      ".json": 15,
      ".pth": 1,
      ".typed": 52,
      ".md": 12,
      ".pyx": 95,
      ".build": 26,
      ".so": 338,
      ".pxd": 85,
      ".pxi": 19,
      ".h": 9626,
      ".cpp": 64,
      ".c": 14,
      ".tp": 24,
      ".rst": 16,
      ".jpg": 2,
      ".gz": 104,
      ".csv": 37,
      ".css": 6,
      ".tab": 8,
      ".zi": 2,
      ".12": 11,
      ".10": 1,
      ".2": 2,
      ".11": 4,
      ".9": 9,
      ".4": 2,
      ".1": 8,
      ".hpp": 96,
      ".zip": 1,
      ".egg": 1,
      ".toml": 2,
      ".pyi": 396,
      ".tpl": 7,
      ".PSF": 1,
      ".0": 17,
      ".j2": 2,
      ".js": 71,
      ".map": 5,
      ".gzip": 5,
      ".pkl": 11,
      ".bz2": 10,
      ".npy": 31,
      ".z": 3,
      ".xz": 5,
      ".lzma": 5,
      ".yaml": 6,
      ".cu": 9,
      ".ini": 4,
      ".bzl": 1,
      ".bazel": 1,
      ".in": 1,
      ".pem": 2,
      ".crt": 1,
      ".key": 1,
      ".mo": 1,
      ".po": 1,
      ".xml": 2,
      ".html": 6,
      ".png": 10,
      ".g4": 2,
      ".al": 16,
      ".lark": 2,
      ".xsl": 3,
      ".template": 1,
      ".f90": 55,
      ".f": 21,
      ".pyf": 5,
      ".inc": 1,
      ".f95": 1,
      ".a": 2,
      ".pc": 1,
      ".fits": 1,
      ".npz": 22,
      ".woff": 20,
      ".woff2": 39,
      ".ttf": 20,
      ".svg": 6,
      ".gif": 1,
      ".BSD": 2,
      ".APACHE": 2,
      ".cuh": 58,
      ".1801": 6,
      ".cc": 24,
      ".feather": 1,
      ".parquet": 4,
      ".orc": 4,
      ".APACHE2": 1,
      ".MIT": 1,
      ".mjs": 2,
      ".cmake": 31,
      ".sh": 1,
      ".3": 1,
      ".16": 1,
      ".15": 1,
      ".markdown-it": 1,
      ".A99": 2,
      ".B99": 2,
      ".asm": 2,
      ".obj": 2,
      ".cmd": 2,
      ".bc": 3,
      ".arff": 16,
      ".sav": 47,
      ".dat": 29,
      ".nc": 3,
      ".wav": 22,
      ".ani": 1,
      ".mat": 109,
      ".exe": 8,
      ".tmpl": 2,
      ".h5": 3,
      ".ps1": 1,
      ".fish": 1,
      ".csh": 1
    },
    "first_commit": "2024-11-27T12:53:23",
    "last_commit": "2024-11-30T11:29:48",
    "time_span_days": 2,
    "commits_per_day": 2.7192792651021893,
    "frequent_words": {
      "i": 3,
      "hope": 1,
      "this": 1,
      "works": 1,
      "new": 1,
      "funtion": 1,
      "fixed": 1,
      "ddids": 1,
      "can't": 1,
      "belive": 1
    },
    "contributor_count": 1
  }
}